iffriendly/__init__.py
iffriendly/interface.py
iffriendly-0.1.1.dist-info/METADATA
iffriendly-0.1.1.dist-info/WHEEL
iffriendly-0.1.1.dist-info/licenses/LICENSE
iffriendly-0.1.1.dist-info/RECORD
