Metadata-Version: 2.4
Name: iffriendly
Version: 0.1.1
Summary: Human-friendly names and metadata for Linux network interfaces
Project-URL: Documentation, https://github.com/jem/iffriendly#readme
Project-URL: Source, https://github.com/jem/iffriendly
Author: jem
License:                                  Apache License
License-File: LICENSE
Keywords: interfaces,linux,metadata,network
Classifier: Development Status :: 4 - Beta
Classifier: Intended Audience :: Developers
Classifier: License :: OSI Approved :: MIT License
Classifier: Operating System :: POSIX :: Linux
Classifier: Programming Language :: Python :: 3
Classifier: Programming Language :: Python :: 3.8
Classifier: Programming Language :: Python :: 3.9
Classifier: Programming Language :: Python :: 3.10
Classifier: Programming Language :: Python :: 3.11
Classifier: Topic :: System :: Networking
Requires-Python: >=3.8
Requires-Dist: mac-vendor-lookup>=0.1.12
Requires-Dist: pydantic>=2.0.0
Requires-Dist: pyroute2>=0.7.0
Provides-Extra: dev
Requires-Dist: black>=24.0.0; extra == 'dev'
Requires-Dist: isort>=5.13.0; extra == 'dev'
Requires-Dist: mypy>=1.8.0; extra == 'dev'
Requires-Dist: pytest-cov>=4.1.0; extra == 'dev'
Requires-Dist: pytest>=8.0.0; extra == 'dev'
